zgautomation/__init__.py
zgautomation/error_handling.py
zgautomation/keys.py
zgautomation/main.py
zgautomation/vars.py
zgautomation-0.0.1.dist-info/METADATA
zgautomation-0.0.1.dist-info/WHEEL
zgautomation-0.0.1.dist-info/top_level.txt
zgautomation-0.0.1.dist-info/RECORD
