Metadata-Version: 2.1
Name: zgautomation
Version: 0.0.1
Summary: A Powerful Module To Interact And Manipulate Browser
Home-page: UNKNOWN
Author: Zaz Yagmi
License: UNKNOWN
Keywords: python,selenium,browser,automation,web scrapping
Platform: UNKNOWN
Requires-Dist: selenium ==4.15.2
Requires-Dist: colorama
Requires-Dist: pathlib
